{
  "$schema" : "https://json-schema.axonivy.com/data-class/12.0.0/data-class.json",
  "simpleName" : "sendDemoMessageData",
  "namespace" : "threema.connector.demo",
  "isBusinessCaseData" : false,
  "fields" : [ {
    "name" : "receiver",
    "type" : "String",
    "modifiers" : [ "PERSISTENT" ]
  }, {
    "name" : "plainMessage",
    "type" : "String",
    "modifiers" : [ "PERSISTENT" ]
  }, {
    "name" : "type",
    "type" : "String",
    "modifiers" : [ "PERSISTENT" ]
  }, {
    "name" : "apiResponse",
    "type" : "List<String>",
    "modifiers" : [ "PERSISTENT" ]
  }, {
    "name" : "publicKey",
    "type" : "String",
    "modifiers" : [ "PERSISTENT" ]
  }, {
    "name" : "privatekey",
    "type" : "String",
    "modifiers" : [ "PERSISTENT" ]
  }, {
    "name" : "sendAnother",
    "type" : "Boolean",
    "modifiers" : [ "PERSISTENT" ]
  } ]
}